pumpe/__init__.py
pumpe/health.py
pumpe/main.py
pumpe/models.py
pumpe/pumps/__init__.py
pumpe/pumps/base.py
pumpe/pumps/model.py
pumpe-0.7.0.dist-info/licenses/LICENSE
pumpe-0.7.0.dist-info/METADATA
pumpe-0.7.0.dist-info/WHEEL
pumpe-0.7.0.dist-info/top_level.txt
pumpe-0.7.0.dist-info/RECORD
