Metadata-Version: 2.4
Name: pumpe
Version: 0.7.0
Summary: Pumping base classes
Requires-Python: >=3.12
License-File: LICENSE
Requires-Dist: aioitertools>=0.12.0
Requires-Dist: anyio>=4.9.0
Requires-Dist: fast-depends>=2.4.12
Requires-Dist: fastapi[standard]>=0.116.1
Requires-Dist: httpx[http2]>=0.28.1
Requires-Dist: pydantic>=2.11.7
Requires-Dist: pydantic-settings>=2.10.1
Requires-Dist: pytest-asyncio>=1.1.0
Requires-Dist: sqlmodel>=0.0.24
Requires-Dist: tenacity>=9.1.2
Requires-Dist: uvicorn>=0.35.0
Dynamic: license-file
